{
  "version": 3,
  "middleware": {
    "/": {
      "files": [
        "server/edge-runtime-webpack.js",
        "server/middleware.js"
      ],
      "name": "middleware",
      "page": "/",
      "matchers": [
        {
          "regexp": "^(?:\\/(_next\\/data\\/[^/]{1,}))?(?:\\/((?!_next\\/static|_next\\/image|favicon.ico|api\\/).*))(\\.json)?[\\/#\\?]?$",
          "originalSource": "/((?!_next/static|_next/image|favicon.ico|api/).*)"
        }
      ],
      "wasm": [],
      "assets": [],
      "env": {
        "__NEXT_BUILD_ID": "c32WA5ifrEBylTI1-scj8",
        "NEXT_SERVER_ACTIONS_ENCRYPTION_KEY": "9d70mmcHClNxaufyh8vCP4btWEk7xcLuzua2acRh9tg=",
        "__NEXT_PREVIEW_MODE_ID": "19d2d13d6cf7c6534c9023f4ccdc4c6e",
        "__NEXT_PREVIEW_MODE_ENCRYPTION_KEY": "53546a996b8a7a716f23614be75774b07d181e2fde279d9f687d47e273fb359b",
        "__NEXT_PREVIEW_MODE_SIGNING_KEY": "674d26c5c3a047cd179c2e9dd35554d171bce447ce3d3fa7133766e9592e690f"
      }
    }
  },
  "functions": {},
  "sortedMiddleware": [
    "/"
  ]
}